README.md
setup.py
alibabacloud_viapiutils20200401/__init__.py
alibabacloud_viapiutils20200401/client.py
alibabacloud_viapiutils20200401/models.py
alibabacloud_viapiutils20200401.egg-info/PKG-INFO
alibabacloud_viapiutils20200401.egg-info/SOURCES.txt
alibabacloud_viapiutils20200401.egg-info/dependency_links.txt
alibabacloud_viapiutils20200401.egg-info/requires.txt
alibabacloud_viapiutils20200401.egg-info/top_level.txt